README.md
setup.py
vrb/__init__.py
vrb/segment_tree.c
vrb/test.py
vrb/vrb.py
vrb.egg-info/PKG-INFO
vrb.egg-info/SOURCES.txt
vrb.egg-info/dependency_links.txt
vrb.egg-info/requires.txt
vrb.egg-info/top_level.txt