Metadata-Version: 1.1
Name: vrb
Version: 0.4
Summary: Variance Reducer Bandit
Home-page: UNKNOWN
Author: Zalan Borsos
Author-email: zalan.borsos@inf.ethz.ch
License: MIT
Keywords: machine learning online variance reduction bandits
Platform: UNKNOWN
Classifier: Development Status :: 4 - Beta
Classifier: License :: OSI Approved :: MIT License
Classifier: Programming Language :: Python :: 2.7
Classifier: Programming Language :: Python :: 3
Classifier: Programming Language :: Python :: 3.5
